[
  {
    "id": "CSST-001",
    "nombre": "Aznavour en castellano 2",
    "artista": "Charles Aznavour",
    "precio_clp": 6900,
    "categoria": "cassette",
    "imagen": "img/CSST-001.webp",
    "estado": "disponible"
  },
  {
    "id": "CSST-002",
    "nombre": "Carlos – Canciones de éxito",
    "artista": "Varios Artistas",
    "precio_clp": 4500,
    "categoria": "cassette",
    "imagen": "img/CSST-002.webp",
    "estado": "disponible"
  },
  {
    "id": "CSST-003",
    "nombre": "Duets",
    "artista": "Elton John",
    "precio_clp": 5500,
    "categoria": "cassette",
    "imagen": "img/CSST-003.webp",
    "estado": "disponible"
  },
  {
    "id": "CSST-004",
    "nombre": "Éxitos para sus fiestas",
    "artista": "Banda Revellón",
    "precio_clp": 4500,
    "categoria": "cassette",
    "imagen": "img/CSST-004.webp",
    "estado": "disponible"
  },
  {
    "id": "CSST-005",
    "nombre": "La soledad",
    "artista": "Carlos Ledermann",
    "precio_clp": 4500,
    "categoria": "cassette",
    "imagen": "img/CSST-005.webp",
    "estado": "disponible"
  },
  {
    "id": "CSST-006",
    "nombre": "Bad English",
    "artista": "Bad English",
    "precio_clp": 7500,
    "categoria": "cassette",
    "imagen": "img/CSST-006.webp",
    "estado": "disponible"
  },
  {
    "id": "CSST-007",
    "nombre": "Così Canta Italia",
    "artista": "Cosimo Ianni P.",
    "precio_clp": 4500,
    "categoria": "cassette",
    "imagen": "img/CSST-007.webp",
    "estado": "disponible"
  },
  {
    "id": "CSST-008",
    "nombre": "Vol. II / Reminiscencias Criollas",
    "artista": "Duo Rey Silva",
    "precio_clp": 5500,
    "categoria": "cassette",
    "imagen": "img/CSST-008.webp",
    "estado": "disponible"
  },
  {
    "id": "CSST-009",
    "nombre": "Gonna Make You Sweat",
    "artista": "C+C Music Factory",
    "precio_clp": 5500,
    "categoria": "cassette",
    "imagen": "img/CSST-009.webp",
    "estado": "disponible"
  },
  {
    "id": "CSST-010",
    "nombre": "Coketeando Vol. II",
    "artista": "Coco Lagos Orquesta & Coros",
    "precio_clp": 4500,
    "categoria": "cassette",
    "imagen": "img/CSST-010.webp",
    "estado": "disponible"
  },
  {
    "id": "CSST-011",
    "nombre": "One to One",
    "artista": "Carole King",
    "precio_clp": 6500,
    "categoria": "cassette",
    "imagen": "img/CSST-011.webp",
    "estado": "disponible"
  },
  {
    "id": "CSST-012",
    "nombre": "Bye Bye Blues",
    "artista": "Bert Kaempfert",
    "precio_clp": 6000,
    "categoria": "cassette",
    "imagen": "img/CSST-012.webp",
    "estado": "disponible"
  },
  {
    "id": "CSST-013",
    "nombre": "Bora Bora",
    "artista": "Os Paralamas do Sucesso",
    "precio_clp": 6500,
    "categoria": "cassette",
    "imagen": "img/CSST-013.webp",
    "estado": "disponible"
  },
  {
    "id": "CSST-014",
    "nombre": "O Canto da Cidade",
    "artista": "Daniela Mercury",
    "precio_clp": 6500,
    "categoria": "cassette",
    "imagen": "img/CSST-014.webp",
    "estado": "disponible"
  },
  {
    "id": "CSST-015",
    "nombre": "Electric Youth",
    "artista": "Debbie Gibson",
    "precio_clp": 6500,
    "categoria": "cassette",
    "imagen": "img/CSST-015.webp",
    "estado": "disponible"
  },
  {
    "id": "CSST-016",
    "nombre": "Screw It",
    "artista": "Danger Danger",
    "precio_clp": 7500,
    "categoria": "cassette",
    "imagen": "img/CSST-016.webp",
    "estado": "disponible"
  },
  {
    "id": "CSST-017",
    "nombre": "Gatos sin uñas",
    "artista": "Donna Summer",
    "precio_clp": 6500,
    "categoria": "cassette",
    "imagen": "img/CSST-017.webp",
    "estado": "disponible"
  },
  {
    "id": "CSST-018",
    "nombre": "Por elegante y buen mozo también",
    "artista": "El Clavel",
    "precio_clp": 4500,
    "categoria": "cassette",
    "imagen": "img/CSST-018.webp",
    "estado": "disponible"
  },
  {
    "id": "CSST-019",
    "nombre": "Greatest Hits",
    "artista": "Dan Fogelberg",
    "precio_clp": 5500,
    "categoria": "cassette",
    "imagen": "img/CSST-019.webp",
    "estado": "disponible"
  },
  {
    "id": "CSST-020",
    "nombre": "Cielos Azules",
    "artista": "Bing Crosby",
    "precio_clp": 4500,
    "categoria": "cassette",
    "imagen": "img/CSST-020.webp",
    "estado": "disponible"
  },
  {
    "id": "CSST-021",
    "nombre": "Canto a la humanidad",
    "artista": "Danny Rivera",
    "precio_clp": 4500,
    "categoria": "cassette",
    "imagen": "img/CSST-021.webp",
    "estado": "disponible"
  },
  {
    "id": "CSST-022",
    "nombre": "The Wanderer",
    "artista": "Donna Summer",
    "precio_clp": 6500,
    "categoria": "cassette",
    "imagen": "img/CSST-022.webp",
    "estado": "disponible"
  },
  {
    "id": "CSST-023",
    "nombre": "En Castellano",
    "artista": "Demis Roussos",
    "precio_clp": 5500,
    "categoria": "cassette",
    "imagen": "img/CSST-023.webp",
    "estado": "disponible"
  },
  {
    "id": "CSST-024",
    "nombre": "Touch the World",
    "artista": "Earth, Wind & Fire",
    "precio_clp": 7000,
    "categoria": "cassette",
    "imagen": "img/CSST-024.webp",
    "estado": "disponible"
  },
  {
    "id": "CSST-025",
    "nombre": "Eduardo Peralta",
    "artista": "Eduardo Peralta",
    "precio_clp": 5500,
    "categoria": "cassette",
    "imagen": "img/CSST-025.webp",
    "estado": "disponible"
  },
  {
    "id": "CSST-026",
    "nombre": "Candle in the Wind – The Elton John Story",
    "artista": "The Twilight Orchestra",
    "precio_clp": 4500,
    "categoria": "cassette",
    "imagen": "img/CSST-026.webp",
    "estado": "disponible"
  },
  {
    "id": "CSST-027",
    "nombre": "Selección Especial",
    "artista": "Enrique Guzmán",
    "precio_clp": 5000,
    "categoria": "cassette",
    "imagen": "img/CSST-027.webp",
    "estado": "disponible"
  },
  {
    "id": "CSST-028",
    "nombre": "Amante Gaviota",
    "artista": "Dyango",
    "precio_clp": 5500,
    "categoria": "cassette",
    "imagen": "img/CSST-028.webp",
    "estado": "disponible"
  },
  {
    "id": "CSST-029",
    "nombre": "Luz Azul",
    "artista": "Denise de Kalafe",
    "precio_clp": 5000,
    "categoria": "cassette",
    "imagen": "img/CSST-029.webp",
    "estado": "disponible"
  }
]
